Metadata-Version: 2.1
Name: Pakiet-Michala
Version: 0.0.0
Summary: Kilka przydatnych funkcji zwracających czas w różnych postaciach
Home-page: https://pypi.python.org/pypi
Author: Michal Mi
Author-email: m.p.milinski@gmail.com
License: MIT
Platform: UNKNOWN
